stepmotor/__init__.py
stepmotor/parallelport.py
stepmotor/stepmotor.py
stepmotor-0.1.0.dist-info/DESCRIPTION.rst
stepmotor-0.1.0.dist-info/METADATA
stepmotor-0.1.0.dist-info/RECORD
stepmotor-0.1.0.dist-info/WHEEL
stepmotor-0.1.0.dist-info/metadata.json
stepmotor-0.1.0.dist-info/top_level.txt
