Metadata-Version: 2.0
Name: stepmotor
Version: 0.1.0
Summary: A package for controll step motors with parallel port
Home-page: https://github.com/alejandroalfonsoyero/stepmotor
Author: Alejandro Alfonso Yero
Author-email: alejandroalfonso1994@gmail.com
License: UNKNOWN
Platform: UNKNOWN
Classifier: Programming Language :: Python :: 3
Classifier: License :: OSI Approved :: MIT License
Classifier: Operating System :: OS Independent
